pymc.py
pymcops/__init__.py
pymcops/pymc.py
pymcops/test_pymc.py
pymcops-0.0.2.dist-info/LICENSE
pymcops-0.0.2.dist-info/METADATA
pymcops-0.0.2.dist-info/WHEEL
pymcops-0.0.2.dist-info/top_level.txt
pymcops-0.0.2.dist-info/RECORD
