Metadata-Version: 2.1
Name: pymcops
Version: 0.0.2
Summary: pymcops
Author: Danh Phan
Author-email: danh.phan.mq@gmail.com
Classifier: Programming Language :: Python
Classifier: Programming Language :: Python :: 3
Classifier: Programming Language :: Python :: 3.8
Classifier: Programming Language :: Python :: 3.9
Classifier: Programming Language :: Python :: 3.10
Classifier: Operating System :: OS Independent
License-File: LICENSE
